xcsv/utils/__init__.py
xcsv/utils/__main__.py
xcsv_utils-0.1.1.dist-info/entry_points.txt
xcsv_utils-0.1.1.dist-info/LICENSE
xcsv_utils-0.1.1.dist-info/WHEEL
xcsv_utils-0.1.1.dist-info/METADATA
xcsv_utils-0.1.1.dist-info/RECORD
